{"is_packed":false,"types":[{"name":"SomeOtherType","fields":[{"name":"a","type":"Primitive","type_index":10,"offset":0,"padding_size":0}]},{"name":"Test","fields":[{"name":"b","type":"Primitive","type_index":6,"offset":0,"padding_size":0},{"name":"a","type":"Array","type_index":0,"offset":4,"padding_size":0}]},{"name":"SomeStruct","fields":[{"name":"some_bool","type":"Primitive","type_index":0,"offset":0,"padding_size":0},{"name":"some_uint","type":"Primitive","type_index":4,"offset":2,"padding_size":0},{"name":"some_float","type":"Primitive","type_index":9,"offset":4,"padding_size":0},{"name":"some_int","type":"Primitive","type_index":7,"offset":8,"padding_size":0},{"name":"some_pointer","type":"Pointer","type_index":0,"offset":16,"padding_size":0},{"name":"some_other_type","type":"Data","type_index":0,"offset":24,"padding_size":0},{"name":"some_other_type_array","type":"Array","type_index":2,"offset":32,"padding_size":0},{"name":"some_other_type_vector","type":"Vector","type_index":0,"offset":56,"padding_size":0},{"name":"some_string","type":"String","type_index":0,"offset":80,"padding_size":0},{"name":"some_float_array","type":"Array","type_index":1,"offset":104,"padding_size":0}]}],"enums":[{"name":"Color","variants":["Red","Green","Blue"]}],"unions":[{"name":"SomeUnion","possible_types":[[0,"Enum"],[2,"Data"]]}],"arrays":[{"inner_type":"Primitive","inner_type_index":2,"len":69},{"inner_type":"Primitive","inner_type_index":9,"len":10},{"inner_type":"Data","inner_type_index":0,"len":3}],"pointers":[{"inner_type":"Data","inner_type_index":0},{"inner_type":"Data","inner_type_index":0}],"vectors":[{"inner_type":"Data","inner_type_index":0}],"functions":[]}